rovio_ingest/__init__.py
rovio_ingest/extensions/__init__.py
rovio_ingest/extensions/dataframe_extension.py
rovio_ingest-1.0.7.dist-info/METADATA
rovio_ingest-1.0.7.dist-info/WHEEL
rovio_ingest-1.0.7.dist-info/RECORD
