Metadata-Version: 2.1
Name: rovio-ingest
Version: 1.0.7
Summary: 
License: Apache-2.0
Author: Vivek Balakrishnan
Author-email: vivek.balakrishnan@rovio.com
Requires-Python: >=3.9,<4.0
Classifier: License :: OSI Approved :: Apache Software License
Classifier: Programming Language :: Python :: 3
Classifier: Programming Language :: Python :: 3.9
Classifier: Programming Language :: Python :: 3.10
Classifier: Programming Language :: Python :: 3.11
Requires-Dist: pyspark (>=3.4.1,<4.0.0)
